{
  "nombre": "Demo",
  "largo": 2900,
  "fondo": "sky",
  "cancion": "cancion",
  "plataformas": [
    {
      "tipo": "pisoreductor",
      "desdeX": 1000,
      "desdeY": 210,
      "hastaX": 2700,
      "hastaY": 210,
      "alto": 10,
      "multiplicador_velocidad": 0.5
    },
    {
      "tipo": "pisomultiplicador",
      "desdeX": 400,
      "desdeY": 80,
      "hastaX": 2700,
      "hastaY": 80,
      "alto": 10,
      "multiplicador_velocidad": 2
    },
    {
      "tipo": "pisodoble",
      "desdeX": 0,
      "desdeY": 420,
      "hastaX": 2700,
      "hastaY": 420,
      "alto": 10,
      "multiplicador_velocidad": 1
    }
  ],
  "obstaculos": [],
  "imagenes": [],
  "textos": [
    {
      "texto": "Demo",
      "desdeX": 100,
      "desdeY": 500,
      "pixeles": "30px",
      "color": "blue",
      "fuente": "Arial"
    }
  ],
  "inicio_jugadores": {
    "x": 250,
    "y": 350
  },
  "meta": {
    "x": 2600,
    "y": 0,
    "alto": 600
  }
}